hlcalculator/__init__.py
hlcalculator/__main__.py
hlcalculator/calculator.py
hlcalculator/cli.py
hlcalculator/parser.py
hlcalculator-0.1.1.dist-info/METADATA
hlcalculator-0.1.1.dist-info/WHEEL
hlcalculator-0.1.1.dist-info/entry_points.txt
hlcalculator-0.1.1.dist-info/RECORD
