Metadata-Version: 2.1
Name: hlcalculator
Version: 0.1.1
Summary: A command-line calculator tool that can perform basic arithmetic operations
Home-page: https://github.com/hailv/hlcalculator
License: MIT
Author: yangfan_hailv
Author-email: fan.yang@elestyle.jp
Requires-Python: >=3.12,<4.0
Classifier: License :: OSI Approved :: MIT License
Classifier: Programming Language :: Python :: 3
Classifier: Programming Language :: Python :: 3.12
Classifier: Programming Language :: Python :: 3.13
Project-URL: Repository, https://github.com/hailv/hlcalculator
